[
    {
        "zespoly": [
            "Augsburg",
            "Bayern",
            "Bremen",
            "Dortmund",
            "FC Koln",
            "Frankfurt",
            "Freiburg",
            "Hamburger SV",
            "Hannover",
            "Hertha",
            "Hoffenheim",
            "Leverkusen",
            "Mainz",
            "Monchengladbach",
            "RB Lipsk",
            "Schalke",
            "Stuttgart",
            "Wolfsburg"
        ],
        "kraj": "niemcy",
        "liga": "bundesliga"
    },
    {
        "zespoly": [
            "Alaves",
            "Ath. Bilbao",
            "Atl. Madryt",
            "Barcelona",
            "Betis",
            "Celta Vigo",
            "Eibar",
            "Espanyol",
            "Getafe",
            "Girona",
            "Las Palmas",
            "La Coruna",
            "Leganes",
            "Levante",
            "Malaga",
            "Real Madryt",
            "Real Sociedad",
            "Sevilla",
            "Valencia",
            "Villarreal"
        ],
        "kraj": "hiszpania",
        "liga": "laliga"
    },
    {
        "zespoly": [
            "Amiens",
            "Angers",
            "Bordeaux",
            "Caen",
            "Dijon",
            "Guingamp",
            "Lille",
            "Lyon",
            "Marsylia",
            "Metz",
            "Monaco",
            "Montpellier",
            "Nantes",
            "Nice",
            "PSG",
            "Rennes",
            "Strasbourg",
            "St. Etienne",
            "Toulouse",
            "Troyes"
        ],
        "kraj": "francja",
        "liga": "ligue-1"
    },
    {
        "zespoly": [
            "Arsenal",
            "Bournemouth",
            "Brighton",
            "Burnley",
            "Chelsea",
            "Crystal Palace",
            "Everton",
            "Huddersfield",
            "Leicester",
            "Liverpool",
            "Manchester City",
            "Manchester Utd",
            "Newcastle",
            "Southampton",
            "Stoke",
            "Swansea",
            "Tottenham",
            "Watford",
            "West Brom",
            "West Ham"
        ],
        "kraj": "anglia",
        "liga": "premier-league"
    },
    {
        "zespoly": [
            "Arka Gdynia",
            "Bruk-Bet T.",
            "Cracovia",
            "G\u00f3rnik Zabrze",
            "Jagiellonia Bia\u0142ystok",
            "Korona Kielce",
            "Lechia Gda\u0144sk",
            "Lech Pozna\u0144",
            "Legia Warszawa",
            "Piast Gliwice",
            "Pogo\u0144 Szczecin",
            "Sandecja Nowy S\u0105cz",
            "\u015al\u0105sk Wroc\u0142aw",
            "Wis\u0142a Krak\u00f3w",
            "Wis\u0142a P\u0142ock",
            "Zag\u0142\u0119bie Lubin"
        ],
        "kraj": "polska",
        "liga": "ekstraklasa"
    },
    {
        "zespoly": [
            "AC Milan",
            "AS Roma",
            "Atalanta",
            "Benevento",
            "Bologna",
            "Cagliari",
            "Chievo",
            "Crotone",
            "Fiorentina",
            "Genoa",
            "Inter",
            "Juventus",
            "Lazio",
            "Napoli",
            "Sampdoria",
            "Sassuolo",
            "Spal",
            "Torino",
            "Udinese",
            "Verona"
        ],
        "kraj": "wlochy",
        "liga": "serie-a"
    }
]